LICENSE
MANIFEST.in
README.md
requirements.txt
setup.py
django_istio_opentracing/__init__.py
django_istio_opentracing/middleware.py
django_istio_opentracing/monkey.py
django_istio_opentracing.egg-info/PKG-INFO
django_istio_opentracing.egg-info/SOURCES.txt
django_istio_opentracing.egg-info/dependency_links.txt
django_istio_opentracing.egg-info/requires.txt
django_istio_opentracing.egg-info/top_level.txt