Metadata-Version: 2.1
Name: django-istio-opentracing
Version: 1.0.2
Summary: Django opentracing middleware works with k8s and istio
Home-page: https://github.com/wesdu/django-istio-opentracing
Author: Du Wei
Author-email: pandorid@gmail.com
License: UNKNOWN
Keywords: django,istio,k8s,opentracing
Platform: UNKNOWN
Classifier: License :: OSI Approved :: MIT License
Classifier: Operating System :: OS Independent
Classifier: Framework :: Django :: 1.9
Classifier: Framework :: Django :: 1.10
Classifier: Framework :: Django :: 2.1
Classifier: Framework :: Django :: 2.2
Classifier: Programming Language :: Python
Classifier: Programming Language :: Python :: 2.7
Classifier: Programming Language :: Python :: 3.5
Classifier: Programming Language :: Python :: 3.6
Classifier: Programming Language :: Python :: 3.7
